MANIFEST.in
README.rst
bigquery.txt
db2i.txt
db2i_native.txt
dev.txt
hp3000.txt
mssql.txt
mysql.txt
netsuite.txt
oracle.txt
postgres.txt
redshift.txt
setup.py
snowflake.txt
vertica.txt
concentric/__init__.py
concentric/_version.py
concentric/base.py
concentric/bigquery.py
concentric/db2i.py
concentric/db2i_native.py
concentric/hp3000.py
concentric/hp3000_odbc.py
concentric/jdbc.py
concentric/managers.py
concentric/mssql.py
concentric/mysql.py
concentric/netsuite.py
concentric/odbc.py
concentric/oracle.py
concentric/oracle_db.py
concentric/oracle_db_wrapper.py
concentric/postgres.py
concentric/progress_openedge.py
concentric/redshift.py
concentric/snowflake.py
concentric/vertica.py
concentric.egg-info/PKG-INFO
concentric.egg-info/SOURCES.txt
concentric.egg-info/dependency_links.txt
concentric.egg-info/requires.txt
concentric.egg-info/top_level.txt